joiner/__init__.py
joiner/__main__.py
joiner/cli.py
joiner/const.py
joiner/help_formatter.py
joiner/subtitle_joiner.py
subtitle_joiner-0.1.1.dist-info/DESCRIPTION.rst
subtitle_joiner-0.1.1.dist-info/METADATA
subtitle_joiner-0.1.1.dist-info/RECORD
subtitle_joiner-0.1.1.dist-info/WHEEL
subtitle_joiner-0.1.1.dist-info/entry_points.txt
subtitle_joiner-0.1.1.dist-info/metadata.json
subtitle_joiner-0.1.1.dist-info/top_level.txt
